ouch/__init__.py
ouch-0.0.28.dist-info/licenses/LICENSE
ouch-0.0.28.dist-info/METADATA
ouch-0.0.28.dist-info/WHEEL
ouch-0.0.28.dist-info/top_level.txt
ouch-0.0.28.dist-info/RECORD
