Metadata-Version: 2.4
Name: ouch
Version: 0.0.28
Summary: Odd Utility Collection Hub
Author-email: Francis Lim <thyeem@gmail.com>
Project-URL: Homepage, https://github.com/thyeem/ouch
Keywords: utilities,functional
Classifier: Topic :: Software Development :: Libraries :: Python Modules
Classifier: License :: OSI Approved :: MIT License
Classifier: Programming Language :: Python :: 3
Requires-Python: >=3.6
License-File: LICENSE
Requires-Dist: foc
Dynamic: license-file
